demographer/__init__.py
demographer/baseline_dataset.py
demographer/combo_dataset.py
demographer/demog_dexp.py
demographer/demographer.py
demographer/encoders.py
demographer/encoders_selfreport.py
demographer/ethnicity.py
demographer/ethnicity_neural.py
demographer/ethnicity_selfreport_bert.py
demographer/ethnicity_selfreport_neural.py
demographer/experiment_runner.py
demographer/experiment_runner_selfreport.py
demographer/gender.py
demographer/gender_c.py
demographer/gender_neural.py
demographer/indorg.py
demographer/indorg_dataset.py
demographer/indorg_neural.py
demographer/indorg_temp_dataset.py
demographer/infer_ethnicity_selfreport.py
demographer/infer_neural_indorg.py
demographer/label_mapping.py
demographer/mnist.py
demographer/naacl_twitter.py
demographer/rebalance.py
demographer/selfreport_dataset.py
demographer/train_ethnicity_selfreport.py
demographer/train_neural_indorg.py
demographer/train_simple_indorg.py
demographer/transformer.py
demographer/transformer_indorg.py
demographer/transformer_selfreport.py
demographer/utils.py
demographer/cli/__init__.py
demographer/cli/__main__.py
demographer/cli/process_names.py
demographer/cli/process_tweets.py
demographer/data/census_gender_dct.python2.p
demographer/data/census_gender_dct.python3.p
demographer/data/nam_dict.txt.gz
demographer/models/placeholder.txt
demographer/tflm/__init__.py
demographer/tflm/input_dataset.py
demographer/tflm/optimizer.py
demographer/tflm/symbol_table.py
demographer-1.0.4.dist-info/LICENSE.txt
demographer-1.0.4.dist-info/METADATA
demographer-1.0.4.dist-info/WHEEL
demographer-1.0.4.dist-info/top_level.txt
demographer-1.0.4.dist-info/RECORD
