Metadata-Version: 2.1
Name: demographer
Version: 1.0.4
Summary: Simple name demographics for Twitter names
Home-page: https://bitbucket.org/mdredze/demographer
Author: Zach Wood-Doughty, Paiheng Xu, Xiao Liu, Praateek Mahajan, Rebecca Knowles, Josh Carroll, Mark Dredze
Author-email: mdredze@cs.jhu.edu
License: LICENSE.txt
Download-URL: https://bitbucket.org/mdredze/demographer/get/0.1.2.zip
Platform: UNKNOWN
Requires-Dist: numpy
Requires-Dist: scikit-learn
